kubr/__init__.py
kubr/_version.py
kubr/main.py
kubr/backends/__init__.py
kubr/backends/base.py
kubr/backends/k8s_runner.py
kubr/backends/utils.py
kubr/backends/volcano.py
kubr/commands/__init__.py
kubr/commands/attach.py
kubr/commands/base.py
kubr/commands/desc.py
kubr/commands/logs.py
kubr/commands/ls.py
kubr/commands/rm.py
kubr/commands/run.py
kubr/commands/stat.py
kubr/commands/test.py
kubr/commands/utils/__init__.py
kubr/commands/utils/reply.py
kubr/config/__init__.py
kubr/config/job.py
kubr/config/runner.py
kubr/tests/__init__.py
kubr/tests/test_runner.py
kubr-0.0.5.dist-info/LICENSE
kubr-0.0.5.dist-info/METADATA
kubr-0.0.5.dist-info/WHEEL
kubr-0.0.5.dist-info/entry_points.txt
kubr-0.0.5.dist-info/top_level.txt
kubr-0.0.5.dist-info/RECORD
